aidex_toolkit/__init__.py
aidex_toolkit/__main__.py
aidex_toolkit/project1/__init__.py
aidex_toolkit/project1/advanced_linear_regression.py
aidex_toolkit/project1/simple_linear.py
aidex_toolkit/project2/__init__.py
aidex_toolkit/project2/xor_neural_network_basic.py
aidex_toolkit/project3/__init__.py
aidex_toolkit/project3/binary_logistic_trainer.py
aidex_toolkit/project3/sample_data_loader.py
aidex_toolkit-0.1.2.dist-info/LICENSE
aidex_toolkit-0.1.2.dist-info/METADATA
aidex_toolkit-0.1.2.dist-info/WHEEL
aidex_toolkit-0.1.2.dist-info/entry_points.txt
aidex_toolkit-0.1.2.dist-info/top_level.txt
aidex_toolkit-0.1.2.dist-info/RECORD
