Metadata-Version: 2.1
Name: aidex-toolkit
Version: 0.1.2
Summary: Ai/ML trainings package and guide from scratch with sample data support.
Home-page: https://github.com/Perfect-Aimers-Enterprise/aidex_toolkit.git
Author: Godsave Kawurem
Author-email: godsaveogbidor@gmail.com
License: MIT
Platform: UNKNOWN
Classifier: Programming Language :: Python :: 3
Classifier: License :: OSI Approved :: MIT License
Classifier: Operating System :: OS Independent
Requires-Python: >=3.7
License-File: LICENSE
Requires-Dist: numpy
Requires-Dist: scikit-learn
